{
  "last_update": "2026-03-05 02:50:18 CET",
  "last_update_utc": "2026-03-05 01:50:18 UTC",
  "bots": {
    "BTC": {
      "running": true,
      "pid": "22263",
      "probabilities": {
        "2h_0.5pct": 56.2,
        "4h_0.5pct": 36.0,
        "6h_0.5pct": 55.8,
        "2h_0.5pct_SHORT": 49.3,
        "4h_0.5pct_SHORT": 37.9
      },
      "positions": 0,
      "max_positions": 4,
      "last_price": 72604.31,
      "last_log_time": "2026-03-05 02:49:46",
      "pnl_24h": {
        "realized": -26.2,
        "unrealized": 0,
        "trades": 1,
        "wins": 0,
        "losses": 1,
        "open_positions": [],
        "closed_trades": [
          {
            "direction": "LONG",
            "entry": 68454.15,
            "exit": 68211.54,
            "pnl": -26.2,
            "reason": "TRAILING_STOP",
            "exit_time": "2026-03-04 03:05:18",
            "model": "6h_0.5pct"
          }
        ]
      }
    },
    "MNQ": {
      "running": true,
      "pid": "4210",
      "probabilities": {
        "2h_0.5pct": 38.1,
        "4h_0.5pct": 42.8,
        "2h_0.5pct_SHORT": 12.1,
        "4h_0.5pct_SHORT": 26.7
      },
      "positions": 0,
      "max_positions": 4,
      "last_price": 600.85,
      "last_log_time": "2026-03-03 22:00:01",
      "pnl_24h": {
        "realized": 0,
        "unrealized": 0,
        "trades": 0,
        "wins": 0,
        "losses": 0,
        "open_positions": [],
        "closed_trades": []
      }
    },
    "SPY": {
      "running": true,
      "pid": "4377",
      "probabilities": {
        "4h_0.5pct": 3.2,
        "2h_0.5pct_SHORT": 7.1,
        "4h_0.5pct_SHORT": 11.4
      },
      "positions": 1,
      "max_positions": 3,
      "last_price": 680.11,
      "last_log_time": "2026-03-03 21:59:46",
      "pnl_24h": {
        "realized": 0,
        "unrealized": -17.34,
        "trades": 0,
        "wins": 0,
        "losses": 0,
        "open_positions": [
          {
            "id": "ml_v3_long",
            "direction": "long",
            "entry": 6814.8,
            "current": 6832.14,
            "pnl": -17.34
          }
        ],
        "closed_trades": []
      }
    }
  },
  "parquet_health": {
    "BTC": {
      "healthy": true,
      "bars": 2019,
      "last_timestamp": "2026-03-05 01:45:00",
      "freshness_minutes": 4.8,
      "issues": []
    },
    "QQQ": {
      "healthy": true,
      "bars": 13090,
      "last_timestamp": "2026-03-04 22:55:00",
      "freshness_minutes": 174.8,
      "issues": []
    }
  },
  "signal_match": {
    "BTC": {
      "match": true,
      "differences": {
        "2h_0.5pct": 0.5,
        "4h_0.5pct": 0.8,
        "6h_0.5pct": 0.0,
        "2h_0.5pct_SHORT": 0.3,
        "4h_0.5pct_SHORT": 0.6
      },
      "parquet_probs": {
        "2h_0.5pct": 56.2,
        "4h_0.5pct": 36.0,
        "6h_0.5pct": 55.8,
        "2h_0.5pct_SHORT": 49.3,
        "4h_0.5pct_SHORT": 37.9
      },
      "fresh_probs": {
        "2h_0.5pct": 56.7,
        "4h_0.5pct": 36.8,
        "6h_0.5pct": 55.8,
        "2h_0.5pct_SHORT": 49.0,
        "4h_0.5pct_SHORT": 38.5
      },
      "timestamp": "2026-03-05 01:45:00",
      "indicators": {
        "bb_pct_b": 0.0645,
        "macd": -22.64,
        "macd_signal": -1.36,
        "macd_hist": -21.2811,
        "macd_hist_prev": -9.5966,
        "roc_12": -0.37,
        "roc_threshold": 0.4,
        "long_condition": false,
        "short_condition": false,
        "macd_hist_increasing": false,
        "macd_hist_decreasing": true
      },
      "indicator_signal": false
    },
    "MNQ": {
      "match": true,
      "differences": {
        "2h_0.5pct": 1.4,
        "4h_0.5pct": 0.4,
        "2h_0.5pct_SHORT": 2.1,
        "4h_0.5pct_SHORT": 0.6
      },
      "parquet_probs": {
        "2h_0.5pct": 27.5,
        "4h_0.5pct": 12.9,
        "2h_0.5pct_SHORT": 5.7,
        "4h_0.5pct_SHORT": 8.7
      },
      "fresh_probs": {
        "2h_0.5pct": 26.1,
        "4h_0.5pct": 12.5,
        "2h_0.5pct_SHORT": 7.8,
        "4h_0.5pct_SHORT": 8.1
      },
      "timestamp": "2026-03-04 22:55:00",
      "note": "Compared at common timestamp: 2026-03-04 22:55:00 (parquet latest: 2026-03-04 22:55:00, fresh latest: 2026-03-05 02:35:00)",
      "indicators": {
        "bb_pct_b": 0.3391,
        "bb_condition": true,
        "roc_12": 0.04,
        "macd_hist": 0.024,
        "macd_hist_prev": 0.0325,
        "macd_hist_increasing": false,
        "macd_hist_decreasing": true
      },
      "indicator_signal": true
    },
    "SPY": {
      "match": true,
      "indicators": {
        "rsi": 44.23,
        "rsi_threshold": 40,
        "rsi_condition": false,
        "bb_pct_b": 0.3391,
        "bb_threshold": 0.4,
        "bb_condition": true
      },
      "indicator_signal": false,
      "timestamp": "2026-03-04 22:55:00"
    }
  },
  "backtest": {
    "last_run": "2026-03-05 00:18 UTC",
    "period": "24h",
    "total_signals": 219,
    "long_signals": 0,
    "short_signals": 219,
    "signal_hours": 17,
    "recent_signals": [
      {
        "time": "22:10 UTC",
        "price": 73244.0,
        "model": "4h_0.5pct_SHORT",
        "prob": 71.3
      },
      {
        "time": "22:15 UTC",
        "price": 73210.0,
        "model": "2h_0.5pct_SHORT",
        "prob": 65.5
      },
      {
        "time": "22:15 UTC",
        "price": 73210.0,
        "model": "4h_0.5pct_SHORT",
        "prob": 69.8
      },
      {
        "time": "22:20 UTC",
        "price": 73301.0,
        "model": "2h_0.5pct_SHORT",
        "prob": 68.2
      },
      {
        "time": "22:20 UTC",
        "price": 73301.0,
        "model": "4h_0.5pct_SHORT",
        "prob": 71.2
      },
      {
        "time": "22:25 UTC",
        "price": 73260.0,
        "model": "4h_0.5pct_SHORT",
        "prob": 70.3
      },
      {
        "time": "22:30 UTC",
        "price": 73177.0,
        "model": "4h_0.5pct_SHORT",
        "prob": 70.3
      },
      {
        "time": "22:40 UTC",
        "price": 72917.0,
        "model": "4h_0.5pct_SHORT",
        "prob": 66.4
      },
      {
        "time": "22:45 UTC",
        "price": 72822.0,
        "model": "4h_0.5pct_SHORT",
        "prob": 68.7
      },
      {
        "time": "22:50 UTC",
        "price": 72672.0,
        "model": "4h_0.5pct_SHORT",
        "prob": 65.6
      }
    ],
    "hourly_summary": [
      {
        "hour": "13:00",
        "price": 71477.0,
        "long": 41.0,
        "short": 80.0,
        "signal": "SHORT"
      },
      {
        "hour": "14:00",
        "price": 71621.0,
        "long": 60.0,
        "short": 84.0,
        "signal": "SHORT"
      },
      {
        "hour": "15:00",
        "price": 73397.0,
        "long": 54.0,
        "short": 80.0,
        "signal": "SHORT"
      },
      {
        "hour": "16:00",
        "price": 73295.0,
        "long": 60.0,
        "short": 78.0,
        "signal": "SHORT"
      },
      {
        "hour": "17:00",
        "price": 73219.0,
        "long": 53.0,
        "short": 80.0,
        "signal": "SHORT"
      },
      {
        "hour": "18:00",
        "price": 73694.0,
        "long": 48.0,
        "short": 86.0,
        "signal": "SHORT"
      },
      {
        "hour": "19:00",
        "price": 73611.0,
        "long": 45.0,
        "short": 86.0,
        "signal": "SHORT"
      },
      {
        "hour": "20:00",
        "price": 73020.0,
        "long": 54.0,
        "short": 81.0,
        "signal": "SHORT"
      },
      {
        "hour": "21:00",
        "price": 73310.0,
        "long": 55.0,
        "short": 65.0,
        "signal": "SHORT"
      },
      {
        "hour": "22:00",
        "price": 72706.0,
        "long": 57.0,
        "short": 83.0,
        "signal": "SHORT"
      },
      {
        "hour": "23:00",
        "price": 72667.0,
        "long": 54.0,
        "short": 63.0,
        "signal": null
      },
      {
        "hour": "00:00",
        "price": 72676.0,
        "long": 54.0,
        "short": 42.0,
        "signal": null
      }
    ],
    "actual_trades": [
      {
        "time": "02:32 UTC",
        "direction": "LONG",
        "price": 68454.0,
        "model": "6h_0.5pct",
        "pnl": "-$26",
        "result": "\u274c"
      },
      {
        "time": "00:24 UTC",
        "direction": "LONG",
        "price": 68449.0,
        "model": "6h_0.5pct",
        "pnl": "-$48",
        "result": "\u274c"
      }
    ],
    "matched_hours": 0,
    "missed_hours": 17,
    "trade_count": 2
  },
  "alerts": [],
  "check_count": 233,
  "config": {
    "BTC": {
      "SL_PCT": 0.7,
      "TP_PCT": 1.4,
      "models": [
        "2h_0.5pct",
        "4h_0.5pct",
        "6h_0.5pct",
        "2h_0.5pct_SHORT",
        "4h_0.5pct_SHORT"
      ],
      "thresholds": {
        "2h_0.5pct": 0.4,
        "4h_0.5pct": 0.4,
        "6h_0.5pct": 0.4,
        "2h_0.5pct_SHORT": 0.55,
        "4h_0.5pct_SHORT": 0.55
      },
      "enabled_long": true,
      "enabled_short": true
    },
    "MNQ": {
      "SL_PCT": 0.5,
      "TP_PCT": 1.0,
      "models": [
        "2h_0.5pct",
        "4h_0.5pct",
        "2h_0.5pct_SHORT",
        "4h_0.5pct_SHORT"
      ],
      "thresholds": {
        "2h_0.5pct": 0.5,
        "4h_0.5pct": 0.5,
        "2h_0.5pct_SHORT": 0.5,
        "4h_0.5pct_SHORT": 0.5
      },
      "enabled_long": true,
      "enabled_short": true
    },
    "SPY": {
      "SL_PCT": 0.5,
      "TP_PCT": 1.0,
      "models": [
        "4h_0.5pct",
        "2h_0.5pct_SHORT",
        "4h_0.5pct_SHORT"
      ],
      "thresholds": {
        "4h_0.5pct": 0.65,
        "2h_0.5pct_SHORT": 0.65,
        "4h_0.5pct_SHORT": 0.65
      },
      "indicator_long": {
        "RSI": 40,
        "BB_PCT_B": 0.4
      },
      "ml_v3_threshold": 0.55,
      "enabled_long": true,
      "enabled_short": true
    }
  }
}