{
  "last_update": "2026-01-16 17:01:27 CET",
  "last_update_utc": "2026-01-16 16:01:27 UTC",
  "bots": {
    "BTC": {
      "running": false,
      "pid": null,
      "probabilities": {
        "2h_0.5pct": 17.0,
        "4h_0.5pct": 35.5,
        "6h_0.5pct": 47.3,
        "2h_0.5pct_SHORT": 18.9,
        "4h_0.5pct_SHORT": 40.6
      },
      "positions": 1,
      "max_positions": 4,
      "last_price": 95421.39,
      "last_log_time": "2026-01-16 11:48:17",
      "pnl_24h": {
        "realized": -80.09,
        "unrealized": -106.28,
        "trades": 22,
        "wins": 14,
        "losses": 8,
        "open_positions": [
          {
            "id": "6h_0.5pct",
            "direction": "LONG",
            "entry": 95684.7,
            "current": 94621.95,
            "pnl": -106.28
          }
        ],
        "closed_trades": [
          {
            "direction": "LONG",
            "entry": 95531.07,
            "exit": 95812.9,
            "pnl": 26.25,
            "reason": "TRAILING_STOP",
            "exit_time": "2026-01-16 09:29:55",
            "model": "4h_0.5pct"
          },
          {
            "direction": "LONG",
            "entry": 95740.9,
            "exit": 95788.34,
            "pnl": 2.73,
            "reason": "TIMEOUT",
            "exit_time": "2026-01-16 08:05:22",
            "model": "6h_0.5pct"
          },
          {
            "direction": "LONG",
            "entry": 95546.69,
            "exit": 95828.27,
            "pnl": 26.22,
            "reason": "TRAILING_STOP",
            "exit_time": "2026-01-16 02:31:40",
            "model": "4h_0.5pct"
          },
          {
            "direction": "LONG",
            "entry": 96035.16,
            "exit": 95225.64,
            "pnl": -82.29,
            "reason": "STOP_LOSS",
            "exit_time": "2026-01-15 20:31:16",
            "model": "4h_0.5pct"
          },
          {
            "direction": "LONG",
            "entry": 96280.08,
            "exit": 95604.87,
            "pnl": -69.07,
            "reason": "STOP_LOSS",
            "exit_time": "2026-01-15 20:02:34",
            "model": "6h_0.5pct"
          },
          {
            "direction": "SHORT",
            "entry": 96103.22,
            "exit": 95815.54,
            "pnl": 26.75,
            "reason": "TRAILING_STOP",
            "exit_time": "2026-01-15 19:41:28",
            "model": "indicator_trend"
          },
          {
            "direction": "SHORT",
            "entry": 96280.08,
            "exit": 95991.92,
            "pnl": 26.8,
            "reason": "TRAILING_STOP",
            "exit_time": "2026-01-15 19:33:43",
            "model": "2h_0.5pct_SHORT"
          },
          {
            "direction": "LONG",
            "entry": 96690.67,
            "exit": 96009.74,
            "pnl": -69.63,
            "reason": "STOP_LOSS",
            "exit_time": "2026-01-15 19:33:22",
            "model": "2h_0.5pct"
          },
          {
            "direction": "LONG",
            "entry": 96842.01,
            "exit": 96136.32,
            "pnl": -72.07,
            "reason": "STOP_LOSS",
            "exit_time": "2026-01-15 19:13:00",
            "model": "6h_0.5pct"
          },
          {
            "direction": "SHORT",
            "entry": 96524.0,
            "exit": 96247.84,
            "pnl": 25.6,
            "reason": "TRAILING_STOP",
            "exit_time": "2026-01-15 19:11:38",
            "model": "2h_0.5pct_SHORT"
          },
          {
            "direction": "LONG",
            "entry": 96695.99,
            "exit": 96978.73,
            "pnl": 26.34,
            "reason": "TRAILING_STOP",
            "exit_time": "2026-01-15 18:44:40",
            "model": "2h_0.5pct"
          },
          {
            "direction": "LONG",
            "entry": 96695.38,
            "exit": 96978.73,
            "pnl": 26.4,
            "reason": "TRAILING_STOP",
            "exit_time": "2026-01-15 18:44:40",
            "model": "4h_0.5pct"
          },
          {
            "direction": "SHORT",
            "entry": 96339.56,
            "exit": 97019.52,
            "pnl": -70.02,
            "reason": "STOP_LOSS",
            "exit_time": "2026-01-15 18:42:19",
            "model": "4h_0.5pct_SHORT"
          },
          {
            "direction": "LONG",
            "entry": 96449.13,
            "exit": 96732.5,
            "pnl": 26.4,
            "reason": "TRAILING_STOP",
            "exit_time": "2026-01-15 17:42:16",
            "model": "4h_0.5pct"
          },
          {
            "direction": "SHORT",
            "entry": 96695.99,
            "exit": 96406.75,
            "pnl": 26.9,
            "reason": "TRAILING_STOP",
            "exit_time": "2026-01-15 17:02:57",
            "model": "2h_0.5pct_SHORT"
          },
          {
            "direction": "LONG",
            "entry": 95548.01,
            "exit": 96516.61,
            "pnl": 95.82,
            "reason": "TAKE_PROFIT",
            "exit_time": "2026-01-15 16:58:39",
            "model": "6h_0.5pct"
          },
          {
            "direction": "LONG",
            "entry": 95548.01,
            "exit": 96516.61,
            "pnl": 95.82,
            "reason": "TAKE_PROFIT",
            "exit_time": "2026-01-15 16:58:39",
            "model": "4h_0.5pct"
          },
          {
            "direction": "SHORT",
            "entry": 95732.1,
            "exit": 96444.68,
            "pnl": -73.28,
            "reason": "STOP_LOSS",
            "exit_time": "2026-01-15 16:58:34",
            "model": "2h_0.5pct_SHORT"
          },
          {
            "direction": "SHORT",
            "entry": 96014.58,
            "exit": 95667.99,
            "pnl": 32.64,
            "reason": "TRAILING_STOP",
            "exit_time": "2026-01-15 16:50:37",
            "model": "2h_0.5pct_SHORT"
          },
          {
            "direction": "SHORT",
            "entry": 96014.58,
            "exit": 95667.99,
            "pnl": 32.64,
            "reason": "TRAILING_STOP",
            "exit_time": "2026-01-15 16:50:35",
            "model": "4h_0.5pct_SHORT"
          },
          {
            "direction": "LONG",
            "entry": 96254.85,
            "exit": 95565.0,
            "pnl": -70.51,
            "reason": "STOP_LOSS",
            "exit_time": "2026-01-15 16:48:45",
            "model": "4h_0.5pct"
          },
          {
            "direction": "LONG",
            "entry": 96254.85,
            "exit": 95565.0,
            "pnl": -70.51,
            "reason": "STOP_LOSS",
            "exit_time": "2026-01-15 16:48:43",
            "model": "6h_0.5pct"
          }
        ]
      }
    },
    "MNQ": {
      "running": true,
      "pid": "4210",
      "probabilities": {
        "2h_0.5pct": 7.2,
        "4h_0.5pct": 32.1,
        "2h_0.5pct_SHORT": 0.5,
        "4h_0.5pct_SHORT": 11.7
      },
      "positions": 0,
      "max_positions": 4,
      "last_price": 621.1,
      "last_log_time": "2026-01-16 17:01:21",
      "pnl_24h": {
        "realized": 0,
        "unrealized": 0,
        "trades": 0,
        "wins": 0,
        "losses": 0,
        "open_positions": [],
        "closed_trades": []
      }
    },
    "SPY": {
      "running": true,
      "pid": "4377",
      "probabilities": {
        "4h_0.5pct": 2.9,
        "2h_0.5pct_SHORT": 3.7,
        "4h_0.5pct_SHORT": 8.2
      },
      "positions": 0,
      "max_positions": 3,
      "last_price": 692.0,
      "last_log_time": "2026-01-16 17:01:25",
      "pnl_24h": {
        "realized": 0,
        "unrealized": 0,
        "trades": 0,
        "wins": 0,
        "losses": 0,
        "open_positions": [],
        "closed_trades": []
      }
    }
  },
  "parquet_health": {
    "BTC": {
      "healthy": true,
      "bars": 2016,
      "last_timestamp": "2026-01-16 10:45:00",
      "freshness_minutes": 316.5,
      "issues": [
        "Stale data: 316 min old"
      ]
    },
    "QQQ": {
      "healthy": true,
      "bars": 4540,
      "last_timestamp": "2026-01-16 16:20:00",
      "freshness_minutes": -18.5,
      "issues": []
    }
  },
  "signal_match": {
    "BTC": {
      "match": true,
      "differences": {
        "2h_0.5pct": 2.1,
        "4h_0.5pct": 1.1,
        "6h_0.5pct": 1.4,
        "2h_0.5pct_SHORT": 3.4,
        "4h_0.5pct_SHORT": 0.5
      },
      "parquet_probs": {
        "2h_0.5pct": 17.0,
        "4h_0.5pct": 35.5,
        "6h_0.5pct": 47.3,
        "2h_0.5pct_SHORT": 18.9,
        "4h_0.5pct_SHORT": 40.6
      },
      "fresh_probs": {
        "2h_0.5pct": 19.1,
        "4h_0.5pct": 36.6,
        "6h_0.5pct": 48.7,
        "2h_0.5pct_SHORT": 22.3,
        "4h_0.5pct_SHORT": 41.1
      },
      "timestamp": "2026-01-16 10:45:00",
      "indicators": {
        "bb_pct_b": 0.1445,
        "macd": -77.68,
        "macd_signal": -53.98,
        "macd_hist": -23.6952,
        "macd_hist_prev": -27.67,
        "roc_12": -0.23,
        "roc_threshold": 0.4,
        "long_condition": false,
        "short_condition": false,
        "macd_hist_increasing": true,
        "macd_hist_decreasing": false
      },
      "indicator_signal": false
    },
    "MNQ": {
      "match": true,
      "differences": {
        "2h_0.5pct": 0.0,
        "4h_0.5pct": 0.0,
        "2h_0.5pct_SHORT": 0.0,
        "4h_0.5pct_SHORT": 0.0
      },
      "parquet_probs": {
        "2h_0.5pct": 12.6,
        "4h_0.5pct": 26.9,
        "2h_0.5pct_SHORT": 1.6,
        "4h_0.5pct_SHORT": 13.4
      },
      "fresh_probs": {
        "2h_0.5pct": 12.6,
        "4h_0.5pct": 26.9,
        "2h_0.5pct_SHORT": 1.6,
        "4h_0.5pct_SHORT": 13.4
      },
      "timestamp": "2026-01-16 16:20:00",
      "note": "Re-compared at 2026-01-16 17:00:00 after refresh",
      "indicators": {
        "bb_pct_b": 0.3829,
        "bb_condition": true,
        "roc_12": -0.17,
        "macd_hist": -0.0356,
        "macd_hist_prev": -0.1191,
        "macd_hist_increasing": true,
        "macd_hist_decreasing": false
      },
      "indicator_signal": true,
      "auto_fixed": true
    },
    "SPY": {
      "match": true,
      "indicators": {
        "rsi": 45.98,
        "rsi_threshold": 40,
        "rsi_condition": false,
        "bb_pct_b": 0.3829,
        "bb_threshold": 0.4,
        "bb_condition": true
      },
      "indicator_signal": false,
      "timestamp": "2026-01-16 17:00:00"
    }
  },
  "backtest": {
    "last_run": "2026-01-16 12:00 UTC",
    "period": "24h",
    "total_signals": 45,
    "long_signals": 5,
    "short_signals": 40,
    "signal_hours": 7,
    "recent_signals": [
      {
        "time": "16:50 UTC",
        "price": 96661.0,
        "model": "2h_0.5pct_SHORT",
        "prob": 68.1
      },
      {
        "time": "16:55 UTC",
        "price": 96739.0,
        "model": "2h_0.5pct_SHORT",
        "prob": 65.1
      },
      {
        "time": "17:00 UTC",
        "price": 96692.0,
        "model": "2h_0.5pct_SHORT",
        "prob": 68.8
      },
      {
        "time": "17:10 UTC",
        "price": 96503.0,
        "model": "2h_0.5pct_SHORT",
        "prob": 66.7
      },
      {
        "time": "17:15 UTC",
        "price": 96559.0,
        "model": "2h_0.5pct_SHORT",
        "prob": 69.2
      },
      {
        "time": "09:50 UTC",
        "price": 95633.0,
        "model": "6h_0.5pct",
        "prob": 65.6
      },
      {
        "time": "09:55 UTC",
        "price": 95614.0,
        "model": "6h_0.5pct",
        "prob": 65.1
      },
      {
        "time": "10:00 UTC",
        "price": 95574.0,
        "model": "6h_0.5pct",
        "prob": 65.9
      },
      {
        "time": "10:05 UTC",
        "price": 95547.0,
        "model": "6h_0.5pct",
        "prob": 65.1
      },
      {
        "time": "10:10 UTC",
        "price": 95565.0,
        "model": "6h_0.5pct",
        "prob": 65.2
      }
    ],
    "hourly_summary": [
      {
        "hour": "01:00",
        "price": 95664.0,
        "long": 56.0,
        "short": 32.0,
        "signal": null
      },
      {
        "hour": "02:00",
        "price": 95504.0,
        "long": 48.0,
        "short": 34.0,
        "signal": null
      },
      {
        "hour": "03:00",
        "price": 95355.0,
        "long": 52.0,
        "short": 32.0,
        "signal": null
      },
      {
        "hour": "04:00",
        "price": 95261.0,
        "long": 52.0,
        "short": 29.0,
        "signal": null
      },
      {
        "hour": "05:00",
        "price": 95660.0,
        "long": 43.0,
        "short": 34.0,
        "signal": null
      },
      {
        "hour": "06:00",
        "price": 95741.0,
        "long": 40.0,
        "short": 33.0,
        "signal": null
      },
      {
        "hour": "07:00",
        "price": 95653.0,
        "long": 62.0,
        "short": 30.0,
        "signal": null
      },
      {
        "hour": "08:00",
        "price": 95676.0,
        "long": 59.0,
        "short": 30.0,
        "signal": null
      },
      {
        "hour": "09:00",
        "price": 95614.0,
        "long": 66.0,
        "short": 37.0,
        "signal": "LONG"
      },
      {
        "hour": "10:00",
        "price": 95307.0,
        "long": 66.0,
        "short": 44.0,
        "signal": "LONG"
      },
      {
        "hour": "11:00",
        "price": 95429.0,
        "long": 46.0,
        "short": 45.0,
        "signal": null
      },
      {
        "hour": "12:00",
        "price": 95420.0,
        "long": 47.0,
        "short": 42.0,
        "signal": null
      }
    ],
    "actual_trades": [
      {
        "time": "04:20 UTC",
        "direction": "LONG",
        "price": 95531.0,
        "model": "4h_0.5pct",
        "pnl": "+$26",
        "result": "\u2705"
      },
      {
        "time": "20:35 UTC",
        "direction": "LONG",
        "price": 95547.0,
        "model": "4h_0.5pct",
        "pnl": "+$26",
        "result": "\u2705"
      },
      {
        "time": "20:05 UTC",
        "direction": "LONG",
        "price": 95741.0,
        "model": "6h_0.5pct",
        "pnl": "+$3",
        "result": "\u2705"
      },
      {
        "time": "19:35 UTC",
        "direction": "LONG",
        "price": 96035.0,
        "model": "4h_0.5pct",
        "pnl": "-$82",
        "result": "\u274c"
      },
      {
        "time": "19:20 UTC",
        "direction": "SHORT",
        "price": 96103.0,
        "model": "indicator_trend",
        "pnl": "+$27",
        "result": "\u2705"
      }
    ],
    "matched_hours": 4,
    "missed_hours": 3,
    "trade_count": 31
  },
  "alerts": [
    {
      "time": "2026-01-16T16:01:31.314173",
      "type": "info",
      "message": "MNQ parquet refreshed with 4548 bars"
    }
  ],
  "check_count": 83,
  "config": {
    "BTC": {
      "SL_PCT": 0.7,
      "TP_PCT": 1.4,
      "models": [
        "2h_0.5pct",
        "4h_0.5pct",
        "6h_0.5pct",
        "2h_0.5pct_SHORT",
        "4h_0.5pct_SHORT"
      ],
      "thresholds": {
        "2h_0.5pct": 0.4,
        "4h_0.5pct": 0.4,
        "6h_0.5pct": 0.4,
        "2h_0.5pct_SHORT": 0.55,
        "4h_0.5pct_SHORT": 0.55
      },
      "enabled_long": true,
      "enabled_short": true
    },
    "MNQ": {
      "SL_PCT": 0.5,
      "TP_PCT": 1.0,
      "models": [
        "2h_0.5pct",
        "4h_0.5pct",
        "2h_0.5pct_SHORT",
        "4h_0.5pct_SHORT"
      ],
      "thresholds": {
        "2h_0.5pct": 0.5,
        "4h_0.5pct": 0.5,
        "2h_0.5pct_SHORT": 0.5,
        "4h_0.5pct_SHORT": 0.5
      },
      "enabled_long": true,
      "enabled_short": true
    },
    "SPY": {
      "SL_PCT": 0.5,
      "TP_PCT": 1.0,
      "models": [
        "4h_0.5pct",
        "2h_0.5pct_SHORT",
        "4h_0.5pct_SHORT"
      ],
      "thresholds": {
        "4h_0.5pct": 0.65,
        "2h_0.5pct_SHORT": 0.65,
        "4h_0.5pct_SHORT": 0.65
      },
      "indicator_long": {
        "RSI": 40,
        "BB_PCT_B": 0.4
      },
      "ml_v3_threshold": 0.55,
      "enabled_long": true,
      "enabled_short": true
    }
  }
}