{
  "last_update": "2026-03-25 22:33:33 CET",
  "last_update_utc": "2026-03-25 21:33:33 UTC",
  "bots": {
    "BTC": {
      "running": true,
      "pid": "69286",
      "probabilities": {
        "2h_0.5pct": 32.1,
        "4h_0.5pct": 38.2,
        "6h_0.5pct": 51.6,
        "2h_0.5pct_SHORT": 40.8,
        "4h_0.5pct_SHORT": 39.3
      },
      "positions": 1,
      "max_positions": 4,
      "last_price": 70992.06,
      "last_log_time": "2026-03-25 22:33:25",
      "pnl_24h": {
        "realized": 47.66,
        "unrealized": -24.5,
        "trades": 4,
        "wins": 3,
        "losses": 1,
        "open_positions": [
          {
            "id": "6h_0.5pct",
            "direction": "LONG",
            "entry": 71245.0,
            "current": 70999.96,
            "pnl": -24.5
          }
        ],
        "closed_trades": [
          {
            "direction": "LONG",
            "entry": 71320.0,
            "exit": 70819.33,
            "pnl": -51.74,
            "reason": "STOP_LOSS",
            "exit_time": "2026-03-25 20:56:25",
            "model": "6h_0.5pct"
          },
          {
            "direction": "SHORT",
            "entry": 71620.0,
            "exit": 71264.99,
            "pnl": 33.48,
            "reason": "TRAILING_STOP",
            "exit_time": "2026-03-25 16:00:26",
            "model": "2h_0.5pct_SHORT"
          },
          {
            "direction": "SHORT",
            "entry": 71667.03,
            "exit": 71316.04,
            "pnl": 33.08,
            "reason": "TRAILING_STOP",
            "exit_time": "2026-03-25 13:21:38",
            "model": "2h_0.5pct_SHORT"
          },
          {
            "direction": "LONG",
            "entry": 70975.0,
            "exit": 71321.88,
            "pnl": 32.84,
            "reason": "TRAILING_STOP",
            "exit_time": "2026-03-25 06:11:24",
            "model": "6h_0.5pct"
          }
        ]
      }
    },
    "BTC_TICK": {
      "running": true,
      "pid": "16315",
      "probabilities": {
        "L1_full_wide": 77.1,
        "L3_mom_wide": 42.5,
        "S1_full_cur": 77.7,
        "S3_mr_cur": 43.0,
        "S4_full_tight": 81.9
      },
      "positions": 1,
      "max_positions": 4,
      "last_price": 71004.06,
      "last_log_time": "2026-03-25 21:59:45",
      "pnl_24h": {
        "realized": -152.94,
        "unrealized": 0,
        "trades": 14,
        "wins": 4,
        "losses": 10,
        "open_positions": [],
        "closed_trades": [
          {
            "direction": "LONG",
            "entry": 70770.0,
            "exit": 71059.39,
            "pnl": 28.94,
            "reason": "TRAILING_STOP",
            "exit_time": "2026-03-25T22:17:15",
            "model": "L1_full_wide"
          },
          {
            "direction": "SHORT",
            "entry": 70735.0,
            "exit": 70875.0,
            "pnl": -13.97,
            "reason": "STOP_LOSS",
            "exit_time": "2026-03-25T21:43:16",
            "model": "S1_full_cur"
          },
          {
            "direction": "LONG",
            "entry": 71085.0,
            "exit": 70725.0,
            "pnl": -36.0,
            "reason": "STOP_LOSS",
            "exit_time": "2026-03-25T21:03:32",
            "model": "L1_full_wide"
          },
          {
            "direction": "LONG",
            "entry": 71445.0,
            "exit": 70830.0,
            "pnl": -61.5,
            "reason": "STOP_LOSS",
            "exit_time": "2026-03-25T19:55:50",
            "model": "L1_full_wide"
          },
          {
            "direction": "LONG",
            "entry": 71760.0,
            "exit": 71450.0,
            "pnl": -31.0,
            "reason": "STOP_LOSS",
            "exit_time": "2026-03-25T15:00:46",
            "model": "L1_full_wide"
          },
          {
            "direction": "LONG",
            "entry": 71575.0,
            "exit": 71245.0,
            "pnl": -33.0,
            "reason": "STOP_LOSS",
            "exit_time": "2026-03-25T13:23:06",
            "model": "L1_full_wide"
          },
          {
            "direction": "LONG",
            "entry": 71970.0,
            "exit": 71710.0,
            "pnl": -26.0,
            "reason": "STOP_LOSS",
            "exit_time": "2026-03-25T12:57:29",
            "model": "L1_full_wide"
          },
          {
            "direction": "LONG",
            "entry": 71230.0,
            "exit": 71985.0,
            "pnl": 75.5,
            "reason": "TRAILING_STOP",
            "exit_time": "2026-03-25T12:36:02",
            "model": "L1_full_wide"
          },
          {
            "direction": "SHORT",
            "entry": 71145.0,
            "exit": 71620.0,
            "pnl": -47.18,
            "reason": "STOP_LOSS",
            "exit_time": "2026-03-25T11:57:18",
            "model": "S1_full_cur"
          },
          {
            "direction": "LONG",
            "entry": 70700.0,
            "exit": 71177.82,
            "pnl": 47.78,
            "reason": "TRAILING_STOP",
            "exit_time": "2026-03-25T06:09:06",
            "model": "L1_full_wide"
          },
          {
            "direction": "LONG",
            "entry": 70995.0,
            "exit": 70710.0,
            "pnl": -28.5,
            "reason": "STOP_LOSS",
            "exit_time": "2026-03-25T02:32:50",
            "model": "L1_full_wide"
          },
          {
            "direction": "LONG",
            "entry": 70845.0,
            "exit": 70510.0,
            "pnl": -33.5,
            "reason": "STOP_LOSS",
            "exit_time": "2026-03-25T01:30:30",
            "model": "L1_full_wide"
          },
          {
            "direction": "LONG",
            "entry": 70365.0,
            "exit": 70760.0,
            "pnl": 39.5,
            "reason": "TRAILING_STOP",
            "exit_time": "2026-03-25T00:36:34",
            "model": "L1_full_wide"
          },
          {
            "direction": "LONG",
            "entry": 70515.0,
            "exit": 70175.0,
            "pnl": -34.0,
            "reason": "STOP_LOSS",
            "exit_time": "2026-03-24T23:30:12",
            "model": "L1_full_wide"
          }
        ]
      }
    },
    "BTC_TICK_REVERSE": {
      "running": true,
      "pid": "16946",
      "probabilities": {},
      "positions": 0,
      "max_positions": 4,
      "last_price": 70992.06,
      "last_log_time": "2026-03-25 22:33:25",
      "pnl_24h": {
        "realized": 210.45,
        "unrealized": 0,
        "trades": 13,
        "wins": 10,
        "losses": 3,
        "open_positions": [],
        "closed_trades": [
          {
            "direction": "SHORT",
            "entry": 70750.0,
            "exit": 70750.0,
            "pnl": 0,
            "reason": "TRAILING_STOP",
            "exit_time": "2026-03-25T22:17:20",
            "model": "REV_L1_full_wide"
          },
          {
            "direction": "LONG",
            "entry": 70755.0,
            "exit": 70905.0,
            "pnl": 15.0,
            "reason": "STOP_LOSS",
            "exit_time": "2026-03-25T21:43:20",
            "model": "REV_S1_full_cur"
          },
          {
            "direction": "SHORT",
            "entry": 71060.0,
            "exit": 70750.0,
            "pnl": 31.14,
            "reason": "STOP_LOSS",
            "exit_time": "2026-03-25T21:03:35",
            "model": "REV_L1_full_wide"
          },
          {
            "direction": "SHORT",
            "entry": 71420.0,
            "exit": 70795.0,
            "pnl": 63.05,
            "reason": "STOP_LOSS",
            "exit_time": "2026-03-25T19:55:54",
            "model": "REV_L1_full_wide"
          },
          {
            "direction": "SHORT",
            "entry": 71745.0,
            "exit": 71455.0,
            "pnl": 29.12,
            "reason": "STOP_LOSS",
            "exit_time": "2026-03-25T15:00:50",
            "model": "REV_L1_full_wide"
          },
          {
            "direction": "SHORT",
            "entry": 71535.0,
            "exit": 71280.0,
            "pnl": 25.59,
            "reason": "STOP_LOSS",
            "exit_time": "2026-03-25T13:23:08",
            "model": "REV_L1_full_wide"
          },
          {
            "direction": "SHORT",
            "entry": 71955.0,
            "exit": 71715.0,
            "pnl": 24.08,
            "reason": "STOP_LOSS",
            "exit_time": "2026-03-25T12:57:31",
            "model": "REV_L1_full_wide"
          },
          {
            "direction": "LONG",
            "entry": 71165.0,
            "exit": 71610.0,
            "pnl": 44.5,
            "reason": "STOP_LOSS",
            "exit_time": "2026-03-25T11:57:22",
            "model": "REV_S1_full_cur"
          },
          {
            "direction": "SHORT",
            "entry": 70675.0,
            "exit": 71220.0,
            "pnl": -54.08,
            "reason": "TRAILING_STOP",
            "exit_time": "2026-03-25T06:09:09",
            "model": "REV_L1_full_wide"
          },
          {
            "direction": "SHORT",
            "entry": 70965.0,
            "exit": 70735.0,
            "pnl": 23.07,
            "reason": "STOP_LOSS",
            "exit_time": "2026-03-25T02:32:54",
            "model": "REV_L1_full_wide"
          },
          {
            "direction": "SHORT",
            "entry": 70760.0,
            "exit": 70555.0,
            "pnl": 20.56,
            "reason": "STOP_LOSS",
            "exit_time": "2026-03-25T01:30:34",
            "model": "REV_L1_full_wide"
          },
          {
            "direction": "SHORT",
            "entry": 70335.0,
            "exit": 70775.0,
            "pnl": -43.73,
            "reason": "TRAILING_STOP",
            "exit_time": "2026-03-25T00:36:37",
            "model": "REV_L1_full_wide"
          },
          {
            "direction": "SHORT",
            "entry": 70490.0,
            "exit": 70170.0,
            "pnl": 32.15,
            "reason": "STOP_LOSS",
            "exit_time": "2026-03-24T23:30:16",
            "model": "REV_L1_full_wide"
          }
        ]
      }
    },
    "MNQ_GLOBAL": {
      "running": true,
      "pid": "31288",
      "probabilities": {
        "RF": 55.0
      },
      "positions": 0,
      "max_positions": 1,
      "last_price": null,
      "last_log_time": "2026-03-25 15:30:09",
      "today_signal": "SKIP",
      "rf_prob": 0.55,
      "position_detail": null,
      "week_stats": {
        "trades": 0,
        "wins": 0,
        "losses": 0,
        "win_rate": 0,
        "pnl": 0
      },
      "pnl_24h": {
        "realized": 0,
        "unrealized": 0,
        "trades": 0,
        "wins": 0,
        "losses": 0,
        "open_positions": [],
        "closed_trades": []
      }
    },
    "BTC_TPSL": {
      "running": true,
      "pid": "17257",
      "probabilities": {
        "Vol": 1.07
      },
      "positions": 1,
      "max_positions": 3,
      "last_price": 71003.44,
      "last_log_time": "2026-03-25 21:59:24",
      "strategy_positions": [
        {
          "strategy": "M2_long_hgb60",
          "direction": "LONG",
          "entry_price": 70810.0,
          "tp_price": 71518.1,
          "sl_price": 70455.95,
          "entry_time": "2026-03-25T19:58:42.006765"
        }
      ],
      "week_stats": {
        "trades": 1,
        "wins": 0,
        "losses": 1,
        "win_rate": 0.0,
        "pnl": -30.0,
        "by_strategy": {
          "M2_rf55_vol": {
            "trades": 1,
            "wins": 0,
            "losses": 1,
            "win_rate": 0.0,
            "pnl": -30.0
          }
        }
      },
      "pnl_24h": {
        "realized": 0,
        "unrealized": 0,
        "trades": 0,
        "wins": 0,
        "losses": 0,
        "open_positions": [],
        "closed_trades": []
      }
    }
  },
  "parquet_health": {
    "BTC": {
      "healthy": true,
      "bars": 2024,
      "last_timestamp": "2026-03-25 21:30:00",
      "freshness_minutes": 3.4,
      "issues": []
    },
    "QQQ": {
      "healthy": true,
      "bars": 13596,
      "last_timestamp": "2026-03-25 21:50:00",
      "freshness_minutes": -16.6,
      "issues": []
    }
  },
  "signal_match": {
    "BTC": {
      "match": true,
      "differences": {
        "2h_0.5pct": 0.6,
        "4h_0.5pct": 1.8,
        "6h_0.5pct": 3.2,
        "2h_0.5pct_SHORT": 0.9,
        "4h_0.5pct_SHORT": 0.0
      },
      "parquet_probs": {
        "2h_0.5pct": 32.1,
        "4h_0.5pct": 38.2,
        "6h_0.5pct": 51.6,
        "2h_0.5pct_SHORT": 40.8,
        "4h_0.5pct_SHORT": 39.3
      },
      "fresh_probs": {
        "2h_0.5pct": 31.5,
        "4h_0.5pct": 40.0,
        "6h_0.5pct": 54.8,
        "2h_0.5pct_SHORT": 41.7,
        "4h_0.5pct_SHORT": 39.3
      },
      "timestamp": "2026-03-25 21:30:00",
      "indicators": {
        "bb_pct_b": 0.6346,
        "macd": 36.4,
        "macd_signal": 23.21,
        "macd_hist": 13.1889,
        "macd_hist_prev": 20.03,
        "roc_12": 0.35,
        "roc_threshold": 0.4,
        "long_condition": false,
        "short_condition": false,
        "macd_hist_increasing": false,
        "macd_hist_decreasing": true
      },
      "indicator_signal": false
    },
    "MNQ": {
      "match": true,
      "differences": {
        "2h_0.5pct": 0.0,
        "4h_0.5pct": 0.0,
        "2h_0.5pct_SHORT": 0.0,
        "4h_0.5pct_SHORT": 0.0
      },
      "parquet_probs": {
        "2h_0.5pct": 43.6,
        "4h_0.5pct": 34.2,
        "2h_0.5pct_SHORT": 15.7,
        "4h_0.5pct_SHORT": 17.4
      },
      "fresh_probs": {
        "2h_0.5pct": 43.6,
        "4h_0.5pct": 34.2,
        "2h_0.5pct_SHORT": 15.7,
        "4h_0.5pct_SHORT": 17.4
      },
      "timestamp": "2026-03-25 21:50:00",
      "note": "Re-compared at 2026-03-25 21:55:00 after refresh",
      "indicators": {
        "bb_pct_b": 0.615,
        "bb_condition": false,
        "roc_12": -0.02,
        "macd_hist": 0.0482,
        "macd_hist_prev": 0.0398,
        "macd_hist_increasing": true,
        "macd_hist_decreasing": false
      },
      "indicator_signal": false,
      "auto_fixed": true
    },
    "SPY": {
      "match": true,
      "indicators": {
        "rsi": 48.8,
        "rsi_threshold": 40,
        "rsi_condition": false,
        "bb_pct_b": 0.615,
        "bb_threshold": 0.4,
        "bb_condition": false
      },
      "indicator_signal": false,
      "timestamp": "2026-03-25 21:55:00"
    }
  },
  "backtest": {
    "last_run": "2026-03-25 18:02 UTC",
    "period": "24h",
    "total_signals": 41,
    "long_signals": 1,
    "short_signals": 40,
    "signal_hours": 8,
    "recent_signals": [
      {
        "time": "14:45 UTC",
        "price": 71399.0,
        "model": "2h_0.5pct_SHORT",
        "prob": 69.3
      },
      {
        "time": "14:50 UTC",
        "price": 71341.0,
        "model": "2h_0.5pct_SHORT",
        "prob": 67.5
      },
      {
        "time": "15:15 UTC",
        "price": 70688.0,
        "model": "2h_0.5pct_SHORT",
        "prob": 66.1
      },
      {
        "time": "15:20 UTC",
        "price": 70935.0,
        "model": "2h_0.5pct_SHORT",
        "prob": 65.0
      },
      {
        "time": "16:25 UTC",
        "price": 71507.0,
        "model": "2h_0.5pct_SHORT",
        "prob": 71.3
      },
      {
        "time": "16:30 UTC",
        "price": 71423.0,
        "model": "2h_0.5pct_SHORT",
        "prob": 65.5
      },
      {
        "time": "16:35 UTC",
        "price": 71636.0,
        "model": "2h_0.5pct_SHORT",
        "prob": 70.3
      },
      {
        "time": "16:40 UTC",
        "price": 71468.0,
        "model": "2h_0.5pct_SHORT",
        "prob": 65.4
      },
      {
        "time": "16:55 UTC",
        "price": 71324.0,
        "model": "2h_0.5pct_SHORT",
        "prob": 67.8
      },
      {
        "time": "17:00 UTC",
        "price": 71306.0,
        "model": "2h_0.5pct_SHORT",
        "prob": 65.5
      }
    ],
    "hourly_summary": [
      {
        "hour": "07:00",
        "price": 70927.0,
        "long": 62.0,
        "short": 38.0,
        "signal": null
      },
      {
        "hour": "08:00",
        "price": 71248.0,
        "long": 64.0,
        "short": 50.0,
        "signal": null
      },
      {
        "hour": "09:00",
        "price": 71346.0,
        "long": 57.0,
        "short": 52.0,
        "signal": null
      },
      {
        "hour": "10:00",
        "price": 71501.0,
        "long": 61.0,
        "short": 59.0,
        "signal": null
      },
      {
        "hour": "11:00",
        "price": 71679.0,
        "long": 58.0,
        "short": 68.0,
        "signal": "SHORT"
      },
      {
        "hour": "12:00",
        "price": 71715.0,
        "long": 51.0,
        "short": 72.0,
        "signal": "SHORT"
      },
      {
        "hour": "13:00",
        "price": 71581.0,
        "long": 52.0,
        "short": 72.0,
        "signal": "SHORT"
      },
      {
        "hour": "14:00",
        "price": 71234.0,
        "long": 66.0,
        "short": 73.0,
        "signal": "LONG"
      },
      {
        "hour": "15:00",
        "price": 70833.0,
        "long": 60.0,
        "short": 66.0,
        "signal": "SHORT"
      },
      {
        "hour": "16:00",
        "price": 71324.0,
        "long": 48.0,
        "short": 71.0,
        "signal": "SHORT"
      },
      {
        "hour": "17:00",
        "price": 70779.0,
        "long": 58.0,
        "short": 65.0,
        "signal": "SHORT"
      },
      {
        "hour": "18:00",
        "price": 70808.0,
        "long": 51.0,
        "short": 55.0,
        "signal": null
      }
    ],
    "actual_trades": [
      {
        "time": "13:37 UTC",
        "direction": "SHORT",
        "price": 71620.0,
        "model": "2h_0.5pct_SHORT",
        "pnl": "+$33",
        "result": "\u2705"
      },
      {
        "time": "12:56 UTC",
        "direction": "SHORT",
        "price": 71667.0,
        "model": "2h_0.5pct_SHORT",
        "pnl": "+$33",
        "result": "\u2705"
      },
      {
        "time": "04:35 UTC",
        "direction": "LONG",
        "price": 70975.0,
        "model": "6h_0.5pct",
        "pnl": "+$33",
        "result": "\u2705"
      }
    ],
    "matched_hours": 2,
    "missed_hours": 6,
    "trade_count": 3
  },
  "alerts": [
    {
      "time": "2026-03-25T21:33:32.921462",
      "type": "info",
      "message": "MNQ parquet refreshed with 13597 bars"
    }
  ],
  "check_count": 92,
  "config": {
    "BTC": {
      "SL_PCT": 0.7,
      "TP_PCT": 1.4,
      "models": [
        "2h_0.5pct",
        "4h_0.5pct",
        "6h_0.5pct",
        "2h_0.5pct_SHORT",
        "4h_0.5pct_SHORT"
      ],
      "thresholds": {
        "2h_0.5pct": 0.4,
        "4h_0.5pct": 0.4,
        "6h_0.5pct": 0.4,
        "2h_0.5pct_SHORT": 0.55,
        "4h_0.5pct_SHORT": 0.55
      },
      "enabled_long": true,
      "enabled_short": true
    },
    "BTC_TICK": {
      "SL_PCT_LONG": 0.3,
      "TS_ACT_LONG": 0.4,
      "TS_TRAIL_LONG": 0.1,
      "SL_PCT_SHORT": 0.2,
      "TS_ACT_SHORT": 0.25,
      "TS_TRAIL_SHORT": 0.05,
      "models": [
        "L1_full_wide",
        "L3_mom_wide",
        "S1_full_cur",
        "S3_mr_cur",
        "S4_full_tight"
      ],
      "thresholds": {
        "L1_full_wide": 0.6,
        "L3_mom_wide": 0.6,
        "S1_full_cur": 0.7,
        "S3_mr_cur": 0.7,
        "S4_full_tight": 0.7
      },
      "entry_long": "any of L1/L3 >= 60%",
      "entry_short": "2+ of S1/S3/S4 >= 70% (majority vote)",
      "enabled_long": true,
      "enabled_short": true,
      "db_path": "tick_trades.db"
    },
    "BTC_TICK_REVERSE": {
      "SL_PCT_LONG": 0.2,
      "TS_ACT_LONG": 0.35,
      "TS_TRAIL_LONG": 0.15,
      "SL_PCT_SHORT": 0.45,
      "TS_ACT_SHORT": 0.5,
      "TS_TRAIL_SHORT": 0.15,
      "models": [
        "L1_full_wide",
        "L3_mom_wide",
        "S1_full_cur",
        "S3_mr_cur",
        "S4_full_tight"
      ],
      "thresholds": {
        "L1_full_wide": 0.55,
        "S1_full_cur": 0.7,
        "S3_mr_cur": 0.7,
        "S4_full_tight": 0.7
      },
      "entry_long": "REVERSE: SHORT models 2+ agree \u2192 enter LONG",
      "entry_short": "REVERSE: LONG model L1 >= 55% \u2192 enter SHORT",
      "enabled_long": true,
      "enabled_short": true,
      "db_path": "tick_trades_reverse.db"
    },
    "MNQ_GLOBAL": {
      "SL_PCT": 0.5,
      "TP_PCT": 1.0,
      "model": "RF (rf_global_signal.pkl)",
      "threshold": 0.55,
      "entry_long": "RF prob > 55% at 10:30 ET",
      "entry_short": "RF prob < 45% at 10:30 ET",
      "entry_time": "10:30 ET",
      "exit_time": "15:55 ET",
      "max_trades_per_day": 1,
      "position_size": "1 MNQ ($2/point)",
      "enabled_long": true,
      "enabled_short": true,
      "db_path": "mnq_global_trades.db",
      "position_file": "mnq_global_position.json"
    },
    "BTC_TPSL": {
      "SL_PCT": 0.5,
      "TP_PCT": 1.0,
      "strategies": [
        "M1_long_hgb70",
        "M2_long_hgb60"
      ],
      "entry_M1": "LONG HGB P(TP)>70% (81.5% WR, +0.72% EV)",
      "entry_M2": "LONG HGB P(TP)>60% (62.2% WR, +0.43% EV)",
      "max_positions": 2,
      "enabled_long": true,
      "enabled_short": true,
      "db_path": "tpsl_trades.db"
    }
  }
}