{
  "last_update": "2026-03-03 16:44:01 CET",
  "last_update_utc": "2026-03-03 15:44:01 UTC",
  "bots": {
    "BTC": {
      "running": true,
      "pid": "22263",
      "probabilities": {
        "2h_0.5pct": 55.0,
        "4h_0.5pct": 67.3,
        "6h_0.5pct": 63.8,
        "2h_0.5pct_SHORT": 59.9,
        "4h_0.5pct_SHORT": 51.6
      },
      "positions": 0,
      "max_positions": 4,
      "last_price": 67518.09,
      "last_log_time": "2026-03-03 16:43:47",
      "pnl_24h": {
        "realized": 89.67,
        "unrealized": 0,
        "trades": 11,
        "wins": 8,
        "losses": 3,
        "open_positions": [],
        "closed_trades": [
          {
            "direction": "LONG",
            "entry": 67147.75,
            "exit": 67474.5,
            "pnl": 30.81,
            "reason": "TRAILING_STOP",
            "exit_time": "2026-03-03 15:31:26",
            "model": "4h_0.5pct"
          },
          {
            "direction": "LONG",
            "entry": 67191.69,
            "exit": 67474.5,
            "pnl": 26.38,
            "reason": "TRAILING_STOP",
            "exit_time": "2026-03-03 15:31:24",
            "model": "6h_0.5pct"
          },
          {
            "direction": "LONG",
            "entry": 67349.92,
            "exit": 67139.82,
            "pnl": -22.96,
            "reason": "STOP_LOSS",
            "exit_time": "2026-03-03 14:05:11",
            "model": "6h_0.5pct"
          },
          {
            "direction": "LONG",
            "entry": 67075.99,
            "exit": 67266.64,
            "pnl": 17.1,
            "reason": "TRAILING_STOP",
            "exit_time": "2026-03-03 13:06:06",
            "model": "6h_0.5pct"
          },
          {
            "direction": "LONG",
            "entry": 67044.81,
            "exit": 67242.38,
            "pnl": 17.8,
            "reason": "TRAILING_STOP",
            "exit_time": "2026-03-03 13:05:06",
            "model": "4h_0.5pct"
          },
          {
            "direction": "LONG",
            "entry": 69382.89,
            "exit": 69166.66,
            "pnl": -23.58,
            "reason": "STOP_LOSS",
            "exit_time": "2026-03-02 16:53:23",
            "model": "2h_0.5pct"
          },
          {
            "direction": "LONG",
            "entry": 68500.0,
            "exit": 68294.1,
            "pnl": -22.55,
            "reason": "STOP_LOSS",
            "exit_time": "2026-03-02 16:16:08",
            "model": "2h_0.5pct"
          },
          {
            "direction": "LONG",
            "entry": 67806.15,
            "exit": 67991.92,
            "pnl": 16.61,
            "reason": "TRAILING_STOP",
            "exit_time": "2026-03-02 16:11:32",
            "model": "4h_0.5pct"
          },
          {
            "direction": "LONG",
            "entry": 67308.29,
            "exit": 67489.08,
            "pnl": 16.11,
            "reason": "TRAILING_STOP",
            "exit_time": "2026-03-02 16:07:21",
            "model": "4h_0.5pct"
          },
          {
            "direction": "LONG",
            "entry": 67005.29,
            "exit": 67184.39,
            "pnl": 15.94,
            "reason": "TRAILING_STOP",
            "exit_time": "2026-03-02 16:00:32",
            "model": "4h_0.5pct"
          },
          {
            "direction": "LONG",
            "entry": 67001.06,
            "exit": 67200.8,
            "pnl": 18.01,
            "reason": "TRAILING_STOP",
            "exit_time": "2026-03-02 15:50:54",
            "model": "4h_0.5pct"
          }
        ]
      }
    },
    "MNQ": {
      "running": true,
      "pid": "4210",
      "probabilities": {
        "2h_0.5pct": 8.0,
        "4h_0.5pct": 20.0,
        "2h_0.5pct_SHORT": 8.8,
        "4h_0.5pct_SHORT": 56.2
      },
      "positions": 2,
      "max_positions": 4,
      "last_price": 594.18,
      "last_log_time": "2026-03-03 16:43:51",
      "pnl_24h": {
        "realized": 0,
        "unrealized": 78.69,
        "trades": 0,
        "wins": 0,
        "losses": 0,
        "open_positions": [
          {
            "id": "trend_follow_short",
            "direction": "short",
            "entry": 24580.74,
            "current": 24445.2,
            "pnl": 135.55
          },
          {
            "id": "4h_0.5pct_SHORT",
            "direction": "short",
            "entry": 24388.34,
            "current": 24445.2,
            "pnl": -56.86
          }
        ],
        "closed_trades": []
      }
    },
    "SPY": {
      "running": true,
      "pid": "4377",
      "probabilities": {
        "4h_0.5pct": 3.2,
        "2h_0.5pct_SHORT": 7.1,
        "4h_0.5pct_SHORT": 11.4
      },
      "positions": 1,
      "max_positions": 3,
      "last_price": 672.06,
      "last_log_time": "2026-03-03 16:43:53",
      "pnl_24h": {
        "realized": 0,
        "unrealized": 111.8,
        "trades": 0,
        "wins": 0,
        "losses": 0,
        "open_positions": [
          {
            "id": "ml_v3_long",
            "direction": "long",
            "entry": 6757.1,
            "current": 6645.3,
            "pnl": 111.8
          }
        ],
        "closed_trades": []
      }
    }
  },
  "parquet_health": {
    "BTC": {
      "healthy": true,
      "bars": 2012,
      "last_timestamp": "2026-03-03 15:40:00",
      "freshness_minutes": 3.9,
      "issues": []
    },
    "QQQ": {
      "healthy": true,
      "bars": 4578,
      "last_timestamp": "2026-03-03 16:30:00",
      "freshness_minutes": -46.1,
      "issues": []
    }
  },
  "signal_match": {
    "BTC": {
      "match": true,
      "differences": {
        "2h_0.5pct": 3.3,
        "4h_0.5pct": 0.7,
        "6h_0.5pct": 1.6,
        "2h_0.5pct_SHORT": 1.1,
        "4h_0.5pct_SHORT": 0.1
      },
      "parquet_probs": {
        "2h_0.5pct": 55.0,
        "4h_0.5pct": 67.3,
        "6h_0.5pct": 63.8,
        "2h_0.5pct_SHORT": 59.9,
        "4h_0.5pct_SHORT": 51.6
      },
      "fresh_probs": {
        "2h_0.5pct": 58.3,
        "4h_0.5pct": 66.6,
        "6h_0.5pct": 62.2,
        "2h_0.5pct_SHORT": 58.8,
        "4h_0.5pct_SHORT": 51.5
      },
      "timestamp": "2026-03-03 15:40:00",
      "indicators": {
        "bb_pct_b": 0.9606,
        "macd": 52.61,
        "macd_signal": -51.62,
        "macd_hist": 104.2309,
        "macd_hist_prev": 83.1259,
        "roc_12": 1.62,
        "roc_threshold": 0.4,
        "long_condition": true,
        "short_condition": false,
        "macd_hist_increasing": true,
        "macd_hist_decreasing": false
      },
      "indicator_signal": "LONG"
    },
    "MNQ": {
      "match": true,
      "differences": {
        "2h_0.5pct": 0.0,
        "4h_0.5pct": 0.0,
        "2h_0.5pct_SHORT": 0.0,
        "4h_0.5pct_SHORT": 0.0
      },
      "parquet_probs": {
        "2h_0.5pct": 7.7,
        "4h_0.5pct": 16.4,
        "2h_0.5pct_SHORT": 35.5,
        "4h_0.5pct_SHORT": 52.1
      },
      "fresh_probs": {
        "2h_0.5pct": 7.7,
        "4h_0.5pct": 16.4,
        "2h_0.5pct_SHORT": 35.5,
        "4h_0.5pct_SHORT": 52.1
      },
      "timestamp": "2026-03-03 16:30:00",
      "note": "Re-compared at 2026-03-03 16:40:00 after refresh",
      "indicators": {
        "bb_pct_b": 0.2933,
        "bb_condition": true,
        "roc_12": -0.49,
        "macd_hist": -0.145,
        "macd_hist_prev": -0.2803,
        "macd_hist_increasing": true,
        "macd_hist_decreasing": false
      },
      "indicator_signal": true,
      "auto_fixed": true
    },
    "SPY": {
      "match": true,
      "indicators": {
        "rsi": 28.75,
        "rsi_threshold": 40,
        "rsi_condition": true,
        "bb_pct_b": 0.2933,
        "bb_threshold": 0.4,
        "bb_condition": true
      },
      "indicator_signal": true,
      "timestamp": "2026-03-03 16:40:00"
    }
  },
  "backtest": {
    "last_run": "2026-03-03 12:12 UTC",
    "period": "24h",
    "total_signals": 100,
    "long_signals": 72,
    "short_signals": 28,
    "signal_hours": 17,
    "recent_signals": [
      {
        "time": "08:20 UTC",
        "price": 67932.0,
        "model": "6h_0.5pct",
        "prob": 69.6
      },
      {
        "time": "08:25 UTC",
        "price": 67748.0,
        "model": "6h_0.5pct",
        "prob": 71.1
      },
      {
        "time": "08:30 UTC",
        "price": 67632.0,
        "model": "6h_0.5pct",
        "prob": 73.8
      },
      {
        "time": "08:35 UTC",
        "price": 67508.0,
        "model": "2h_0.5pct",
        "prob": 65.1
      },
      {
        "time": "08:35 UTC",
        "price": 67508.0,
        "model": "6h_0.5pct",
        "prob": 73.8
      },
      {
        "time": "08:40 UTC",
        "price": 67347.0,
        "model": "6h_0.5pct",
        "prob": 73.9
      },
      {
        "time": "08:45 UTC",
        "price": 67144.0,
        "model": "6h_0.5pct",
        "prob": 71.8
      },
      {
        "time": "08:50 UTC",
        "price": 67107.0,
        "model": "6h_0.5pct",
        "prob": 73.4
      },
      {
        "time": "12:05 UTC",
        "price": 67506.0,
        "model": "2h_0.5pct_SHORT",
        "prob": 68.2
      },
      {
        "time": "12:10 UTC",
        "price": 67884.0,
        "model": "2h_0.5pct_SHORT",
        "prob": 70.0
      }
    ],
    "hourly_summary": [
      {
        "hour": "01:00",
        "price": 68760.0,
        "long": 69.0,
        "short": 59.0,
        "signal": "LONG"
      },
      {
        "hour": "02:00",
        "price": 68512.0,
        "long": 69.0,
        "short": 57.0,
        "signal": "LONG"
      },
      {
        "hour": "03:00",
        "price": 68378.0,
        "long": 55.0,
        "short": 41.0,
        "signal": null
      },
      {
        "hour": "04:00",
        "price": 68123.0,
        "long": 65.0,
        "short": 43.0,
        "signal": "LONG"
      },
      {
        "hour": "05:00",
        "price": 67948.0,
        "long": 69.0,
        "short": 45.0,
        "signal": "LONG"
      },
      {
        "hour": "06:00",
        "price": 68107.0,
        "long": 60.0,
        "short": 41.0,
        "signal": null
      },
      {
        "hour": "07:00",
        "price": 68173.0,
        "long": 64.0,
        "short": 43.0,
        "signal": null
      },
      {
        "hour": "08:00",
        "price": 67003.0,
        "long": 74.0,
        "short": 47.0,
        "signal": "LONG"
      },
      {
        "hour": "09:00",
        "price": 66648.0,
        "long": 51.0,
        "short": 48.0,
        "signal": null
      },
      {
        "hour": "10:00",
        "price": 66860.0,
        "long": 50.0,
        "short": 51.0,
        "signal": null
      },
      {
        "hour": "11:00",
        "price": 67027.0,
        "long": 55.0,
        "short": 54.0,
        "signal": null
      },
      {
        "hour": "12:00",
        "price": 67884.0,
        "long": 55.0,
        "short": 70.0,
        "signal": "SHORT"
      }
    ],
    "actual_trades": [
      {
        "time": "13:00 UTC",
        "direction": "LONG",
        "price": 67076.0,
        "model": "6h_0.5pct",
        "pnl": "+$17",
        "result": "\u2705"
      },
      {
        "time": "12:40 UTC",
        "direction": "LONG",
        "price": 67045.0,
        "model": "4h_0.5pct",
        "pnl": "+$18",
        "result": "\u2705"
      },
      {
        "time": "16:50 UTC",
        "direction": "LONG",
        "price": 69383.0,
        "model": "2h_0.5pct",
        "pnl": "-$24",
        "result": "\u274c"
      },
      {
        "time": "16:15 UTC",
        "direction": "LONG",
        "price": 68500.0,
        "model": "2h_0.5pct",
        "pnl": "-$23",
        "result": "\u274c"
      },
      {
        "time": "16:10 UTC",
        "direction": "LONG",
        "price": 67806.0,
        "model": "4h_0.5pct",
        "pnl": "+$17",
        "result": "\u2705"
      }
    ],
    "matched_hours": 5,
    "missed_hours": 12,
    "trade_count": 13
  },
  "alerts": [
    {
      "time": "2026-03-03T15:44:00.774967",
      "type": "info",
      "message": "MNQ parquet refreshed with 4580 bars"
    }
  ],
  "check_count": 188,
  "config": {
    "BTC": {
      "SL_PCT": 0.7,
      "TP_PCT": 1.4,
      "models": [
        "2h_0.5pct",
        "4h_0.5pct",
        "6h_0.5pct",
        "2h_0.5pct_SHORT",
        "4h_0.5pct_SHORT"
      ],
      "thresholds": {
        "2h_0.5pct": 0.4,
        "4h_0.5pct": 0.4,
        "6h_0.5pct": 0.4,
        "2h_0.5pct_SHORT": 0.55,
        "4h_0.5pct_SHORT": 0.55
      },
      "enabled_long": true,
      "enabled_short": true
    },
    "MNQ": {
      "SL_PCT": 0.5,
      "TP_PCT": 1.0,
      "models": [
        "2h_0.5pct",
        "4h_0.5pct",
        "2h_0.5pct_SHORT",
        "4h_0.5pct_SHORT"
      ],
      "thresholds": {
        "2h_0.5pct": 0.5,
        "4h_0.5pct": 0.5,
        "2h_0.5pct_SHORT": 0.5,
        "4h_0.5pct_SHORT": 0.5
      },
      "enabled_long": true,
      "enabled_short": true
    },
    "SPY": {
      "SL_PCT": 0.5,
      "TP_PCT": 1.0,
      "models": [
        "4h_0.5pct",
        "2h_0.5pct_SHORT",
        "4h_0.5pct_SHORT"
      ],
      "thresholds": {
        "4h_0.5pct": 0.65,
        "2h_0.5pct_SHORT": 0.65,
        "4h_0.5pct_SHORT": 0.65
      },
      "indicator_long": {
        "RSI": 40,
        "BB_PCT_B": 0.4
      },
      "ml_v3_threshold": 0.55,
      "enabled_long": true,
      "enabled_short": true
    }
  }
}