{
  "last_update": "2026-03-16 00:18:21 CET",
  "last_update_utc": "2026-03-15 23:18:21 UTC",
  "bots": {
    "BTC": {
      "running": true,
      "pid": "591",
      "probabilities": {
        "2h_0.5pct": 42.3,
        "4h_0.5pct": 32.4,
        "6h_0.5pct": 40.1,
        "2h_0.5pct_SHORT": 62.8,
        "4h_0.5pct_SHORT": 55.8
      },
      "positions": 0,
      "max_positions": 4,
      "last_price": 72228.17,
      "last_log_time": "2026-03-15 23:39:01",
      "pnl_24h": {
        "realized": -542.85,
        "unrealized": 526.19,
        "trades": 13,
        "wins": 0,
        "losses": 13,
        "open_positions": [
          {
            "id": "legacy_mbt_2",
            "direction": "LONG",
            "entry": 71985.2,
            "current": 72866.66,
            "pnl": 88.15
          },
          {
            "id": "legacy_mbt_3",
            "direction": "LONG",
            "entry": 71985.2,
            "current": 72866.66,
            "pnl": 88.15
          },
          {
            "id": "legacy_mbt_1",
            "direction": "LONG",
            "entry": 72166.87,
            "current": 72866.66,
            "pnl": 69.98
          },
          {
            "id": "legacy_mbt_4",
            "direction": "LONG",
            "entry": 72166.87,
            "current": 72866.66,
            "pnl": 69.98
          },
          {
            "id": "legacy_mbt_5",
            "direction": "LONG",
            "entry": 72166.87,
            "current": 72866.66,
            "pnl": 69.98
          },
          {
            "id": "legacy_mbt_6",
            "direction": "LONG",
            "entry": 72166.87,
            "current": 72866.66,
            "pnl": 69.98
          },
          {
            "id": "legacy_mbt_7",
            "direction": "LONG",
            "entry": 72166.87,
            "current": 72866.66,
            "pnl": 69.98
          }
        ],
        "closed_trades": [
          {
            "direction": "SHORT",
            "entry": 71834.8,
            "exit": 72234.73,
            "pnl": -42.01,
            "reason": "STOP_LOSS",
            "exit_time": "2026-03-15 23:32:41",
            "model": "legacy_mbt_1"
          },
          {
            "direction": "LONG",
            "entry": 72286.45,
            "exit": 71879.91,
            "pnl": -42.45,
            "reason": "STOP_LOSS",
            "exit_time": "2026-03-15 23:11:13",
            "model": "legacy_mbt_1"
          },
          {
            "direction": "LONG",
            "entry": 72286.45,
            "exit": 71879.91,
            "pnl": -42.45,
            "reason": "STOP_LOSS",
            "exit_time": "2026-03-15 23:11:13",
            "model": "legacy_mbt_2"
          },
          {
            "direction": "LONG",
            "entry": 72286.45,
            "exit": 71879.91,
            "pnl": -42.45,
            "reason": "STOP_LOSS",
            "exit_time": "2026-03-15 23:11:13",
            "model": "legacy_mbt_3"
          },
          {
            "direction": "LONG",
            "entry": 72286.45,
            "exit": 71879.91,
            "pnl": -42.45,
            "reason": "STOP_LOSS",
            "exit_time": "2026-03-15 23:11:13",
            "model": "legacy_mbt_4"
          },
          {
            "direction": "LONG",
            "entry": 72250.4,
            "exit": 71879.91,
            "pnl": -38.88,
            "reason": "STOP_LOSS",
            "exit_time": "2026-03-15 23:11:13",
            "model": "legacy_mbt_1"
          },
          {
            "direction": "LONG",
            "entry": 72250.4,
            "exit": 71879.91,
            "pnl": -38.88,
            "reason": "STOP_LOSS",
            "exit_time": "2026-03-15 23:11:13",
            "model": "legacy_mbt_2"
          },
          {
            "direction": "LONG",
            "entry": 72250.4,
            "exit": 71879.91,
            "pnl": -38.88,
            "reason": "STOP_LOSS",
            "exit_time": "2026-03-15 23:11:13",
            "model": "legacy_mbt_3"
          },
          {
            "direction": "LONG",
            "entry": 72250.4,
            "exit": 71879.91,
            "pnl": -38.88,
            "reason": "STOP_LOSS",
            "exit_time": "2026-03-15 23:11:13",
            "model": "legacy_mbt_4"
          },
          {
            "direction": "LONG",
            "entry": 72250.4,
            "exit": 71879.91,
            "pnl": -38.88,
            "reason": "STOP_LOSS",
            "exit_time": "2026-03-15 23:11:13",
            "model": "legacy_mbt_5"
          },
          {
            "direction": "LONG",
            "entry": 72284.2,
            "exit": 71879.91,
            "pnl": -42.22,
            "reason": "STOP_LOSS",
            "exit_time": "2026-03-15 23:11:11",
            "model": "legacy_mbt_2"
          },
          {
            "direction": "LONG",
            "entry": 72284.2,
            "exit": 71879.91,
            "pnl": -42.22,
            "reason": "STOP_LOSS",
            "exit_time": "2026-03-15 23:11:11",
            "model": "legacy_mbt_3"
          },
          {
            "direction": "SHORT",
            "entry": 71489.8,
            "exit": 71991.78,
            "pnl": -52.22,
            "reason": "STOP_LOSS",
            "exit_time": "2026-03-15 23:08:06",
            "model": "legacy_mbt_1"
          }
        ]
      }
    },
    "MNQ": {
      "running": true,
      "pid": "591",
      "probabilities": {
        "2h_0.5pct": 45.8,
        "4h_0.5pct": 44.3,
        "2h_0.5pct_SHORT": 20.0,
        "4h_0.5pct_SHORT": 8.6
      },
      "positions": 2,
      "max_positions": 4,
      "last_price": 590.66,
      "last_log_time": "2026-03-15 23:38:59",
      "pnl_24h": {
        "realized": 0,
        "unrealized": -23.5,
        "trades": 0,
        "wins": 0,
        "losses": 0,
        "open_positions": [
          {
            "id": "2h_0.5pct",
            "direction": "long",
            "entry": 24324.0,
            "current": 24335.75,
            "pnl": -11.75
          },
          {
            "id": "4h_0.5pct",
            "direction": "long",
            "entry": 24324.0,
            "current": 24335.75,
            "pnl": -11.75
          }
        ],
        "closed_trades": []
      }
    },
    "SPY": {
      "running": false,
      "pid": null,
      "probabilities": {
        "4h_0.5pct": 7.1,
        "2h_0.5pct_SHORT": 24.7,
        "4h_0.5pct_SHORT": 23.5
      },
      "positions": 0,
      "max_positions": 3,
      "last_price": 680.1,
      "last_log_time": "2026-03-11 07:32:39",
      "pnl_24h": {
        "realized": 0,
        "unrealized": 0,
        "trades": 0,
        "wins": 0,
        "losses": 0,
        "open_positions": [],
        "closed_trades": []
      }
    },
    "BTC_TICK": {
      "running": true,
      "pid": "600",
      "probabilities": {
        "L1_full_wide": 32.7,
        "L3_mom_wide": 40.2,
        "S1_full_cur": 48.4,
        "S3_mr_cur": 44.5,
        "S4_full_tight": 40.5
      },
      "positions": 1,
      "max_positions": 4,
      "last_price": 72228.17,
      "last_log_time": "2026-03-15 23:39:01",
      "pnl_24h": {
        "realized": -49.5,
        "unrealized": 0,
        "trades": 4,
        "wins": 1,
        "losses": 3,
        "open_positions": [],
        "closed_trades": [
          {
            "direction": "LONG",
            "entry": 71855.0,
            "exit": 72215.0,
            "pnl": 36.0,
            "reason": "TRAILING_STOP",
            "exit_time": "2026-03-15T23:33:34",
            "model": "L1_full_wide"
          },
          {
            "direction": "LONG",
            "entry": 72230.0,
            "exit": 71910.0,
            "pnl": -32.0,
            "reason": "STOP_LOSS",
            "exit_time": "2026-03-15T23:11:11",
            "model": "L1_full_wide"
          },
          {
            "direction": "LONG",
            "entry": 72255.0,
            "exit": 71985.0,
            "pnl": -27.0,
            "reason": "STOP_LOSS",
            "exit_time": "2026-03-15T23:11:05",
            "model": "L1_full_wide"
          },
          {
            "direction": "LONG",
            "entry": 72280.0,
            "exit": 72015.0,
            "pnl": -26.5,
            "reason": "STOP_LOSS",
            "exit_time": "2026-03-15T23:09:48",
            "model": "L1_full_wide"
          }
        ]
      }
    }
  },
  "parquet_health": {
    "BTC": {
      "healthy": true,
      "bars": 2000,
      "last_timestamp": "2026-03-15 22:45:00",
      "freshness_minutes": 33.3,
      "issues": [
        "Stale data: 33 min old"
      ]
    },
    "QQQ": {
      "healthy": true,
      "bars": 13532,
      "last_timestamp": "2026-03-15 23:25:00",
      "freshness_minutes": -6.7,
      "issues": []
    }
  },
  "signal_match": {
    "BTC": {
      "match": true,
      "differences": {
        "2h_0.5pct": 0.0,
        "4h_0.5pct": 2.1,
        "6h_0.5pct": 3.6,
        "2h_0.5pct_SHORT": 1.2,
        "4h_0.5pct_SHORT": 0.2
      },
      "parquet_probs": {
        "2h_0.5pct": 39.4,
        "4h_0.5pct": 34.2,
        "6h_0.5pct": 37.9,
        "2h_0.5pct_SHORT": 66.5,
        "4h_0.5pct_SHORT": 60.5
      },
      "fresh_probs": {
        "2h_0.5pct": 39.4,
        "4h_0.5pct": 32.1,
        "6h_0.5pct": 34.3,
        "2h_0.5pct_SHORT": 67.7,
        "4h_0.5pct_SHORT": 60.7
      },
      "timestamp": "2026-03-15 22:45:00",
      "indicators": {
        "bb_pct_b": 1.0477,
        "macd": 150.97,
        "macd_signal": 109.6,
        "macd_hist": 41.3713,
        "macd_hist_prev": 25.9818,
        "roc_12": 0.61,
        "roc_threshold": 0.4,
        "long_condition": true,
        "short_condition": false,
        "macd_hist_increasing": true,
        "macd_hist_decreasing": false
      },
      "indicator_signal": "LONG"
    },
    "MNQ": {
      "match": true,
      "differences": {},
      "parquet_probs": {
        "2h_0.5pct": 45.8,
        "4h_0.5pct": 44.3,
        "2h_0.5pct_SHORT": 20.1,
        "4h_0.5pct_SHORT": 8.6
      },
      "fresh_probs": {},
      "timestamp": "2026-03-15 23:25:00",
      "note": "Market closed (weekend)",
      "indicators": {},
      "indicator_signal": false
    },
    "SPY": {
      "match": true,
      "indicators": {
        "rsi": 42.5,
        "rsi_threshold": 40,
        "rsi_condition": false,
        "bb_pct_b": 0.2293,
        "bb_threshold": 0.4,
        "bb_condition": true
      },
      "indicator_signal": false,
      "timestamp": "2026-03-15 23:25:00"
    }
  },
  "backtest": {
    "last_run": "2026-03-15 18:17 UTC",
    "period": "24h",
    "total_signals": 0,
    "long_signals": 0,
    "short_signals": 0,
    "signal_hours": 0,
    "recent_signals": [],
    "hourly_summary": [
      {
        "hour": "07:00",
        "price": 71454.0,
        "long": 52.0,
        "short": 38.0,
        "signal": null
      },
      {
        "hour": "08:00",
        "price": 71718.0,
        "long": 59.0,
        "short": 36.0,
        "signal": null
      },
      {
        "hour": "09:00",
        "price": 71791.0,
        "long": 41.0,
        "short": 52.0,
        "signal": null
      },
      {
        "hour": "10:00",
        "price": 71783.0,
        "long": 40.0,
        "short": 54.0,
        "signal": null
      },
      {
        "hour": "11:00",
        "price": 71839.0,
        "long": 57.0,
        "short": 33.0,
        "signal": null
      },
      {
        "hour": "12:00",
        "price": 71610.0,
        "long": 53.0,
        "short": 39.0,
        "signal": null
      },
      {
        "hour": "13:00",
        "price": 71608.0,
        "long": 51.0,
        "short": 55.0,
        "signal": null
      },
      {
        "hour": "14:00",
        "price": 71622.0,
        "long": 47.0,
        "short": 53.0,
        "signal": null
      },
      {
        "hour": "15:00",
        "price": 71481.0,
        "long": 48.0,
        "short": 48.0,
        "signal": null
      },
      {
        "hour": "16:00",
        "price": 71437.0,
        "long": 49.0,
        "short": 48.0,
        "signal": null
      },
      {
        "hour": "17:00",
        "price": 71820.0,
        "long": 55.0,
        "short": 56.0,
        "signal": null
      },
      {
        "hour": "18:00",
        "price": 71743.0,
        "long": 40.0,
        "short": 55.0,
        "signal": null
      }
    ],
    "actual_trades": [],
    "matched_hours": 0,
    "missed_hours": 0,
    "trade_count": 0
  },
  "alerts": [],
  "check_count": 212,
  "config": {
    "BTC": {
      "SL_PCT": 0.7,
      "TP_PCT": 1.4,
      "models": [
        "2h_0.5pct",
        "4h_0.5pct",
        "6h_0.5pct",
        "2h_0.5pct_SHORT",
        "4h_0.5pct_SHORT"
      ],
      "thresholds": {
        "2h_0.5pct": 0.4,
        "4h_0.5pct": 0.4,
        "6h_0.5pct": 0.4,
        "2h_0.5pct_SHORT": 0.55,
        "4h_0.5pct_SHORT": 0.55
      },
      "enabled_long": true,
      "enabled_short": true
    },
    "MNQ": {
      "SL_PCT": 0.5,
      "TP_PCT": 1.0,
      "models": [
        "2h_0.5pct",
        "4h_0.5pct",
        "2h_0.5pct_SHORT",
        "4h_0.5pct_SHORT"
      ],
      "thresholds": {
        "2h_0.5pct": 0.5,
        "4h_0.5pct": 0.5,
        "2h_0.5pct_SHORT": 0.5,
        "4h_0.5pct_SHORT": 0.5
      },
      "enabled_long": true,
      "enabled_short": true
    },
    "SPY": {
      "SL_PCT": 0.5,
      "TP_PCT": 1.0,
      "models": [
        "4h_0.5pct",
        "2h_0.5pct_SHORT",
        "4h_0.5pct_SHORT"
      ],
      "thresholds": {
        "4h_0.5pct": 0.65,
        "2h_0.5pct_SHORT": 0.65,
        "4h_0.5pct_SHORT": 0.65
      },
      "indicator_long": {
        "RSI": 40,
        "BB_PCT_B": 0.4
      },
      "ml_v3_threshold": 0.55,
      "enabled_long": true,
      "enabled_short": true
    },
    "BTC_TICK": {
      "SL_PCT_LONG": 0.3,
      "TS_ACT_LONG": 0.4,
      "TS_TRAIL_LONG": 0.1,
      "SL_PCT_SHORT": 0.2,
      "TS_ACT_SHORT": 0.25,
      "TS_TRAIL_SHORT": 0.05,
      "models": [
        "L1_full_wide",
        "L3_mom_wide",
        "S1_full_cur",
        "S3_mr_cur",
        "S4_full_tight"
      ],
      "thresholds": {
        "L1_full_wide": 0.6,
        "L3_mom_wide": 0.6,
        "S1_full_cur": 0.7,
        "S3_mr_cur": 0.7,
        "S4_full_tight": 0.7
      },
      "entry_long": "any of L1/L3 >= 60%",
      "entry_short": "2+ of S1/S3/S4 >= 70% (majority vote)",
      "enabled_long": true,
      "enabled_short": true,
      "db_path": "tick_trades.db"
    }
  }
}